{
  "indexes": [
    {
      "collectionGroup": "guests",
      "queryScope": "COLLECTION",
      "fields": [
        { "fieldPath": "locationId", "order": "ASCENDING" },
        { "fieldPath": "checkInTime", "order": "DESCENDING" }
      ]
    },
    {
      "collectionGroup": "guests",
      "queryScope": "COLLECTION",
      "fields": [
        { "fieldPath": "locationId", "order": "ASCENDING" },
        { "fieldPath": "checkInTime", "order": "ASCENDING" }
      ]
    },
    {
      "collectionGroup": "guests",
      "queryScope": "COLLECTION",
      "fields": [
        { "fieldPath": "locationId", "order": "ASCENDING" },
        { "fieldPath": "status", "order": "ASCENDING" }
      ]
    },
    {
      "collectionGroup": "guests",
      "queryScope": "COLLECTION",
      "fields": [
        { "fieldPath": "locationId", "order": "ASCENDING" },
        { "fieldPath": "keperluan", "order": "ASCENDING" }
      ]
    },
    {
      "collectionGroup": "guests",
      "queryScope": "COLLECTION",
      "fields": [
        { "fieldPath": "locationId", "order": "ASCENDING" },
        { "fieldPath": "phone", "order": "ASCENDING" },
        { "fieldPath": "status", "order": "ASCENDING" },
        { "fieldPath": "checkInTime", "order": "DESCENDING" }
      ]
    },
    {
      "collectionGroup": "locations",
      "queryScope": "COLLECTION",
      "fields": [
        { "fieldPath": "adminId", "order": "ASCENDING" },
        { "fieldPath": "isActive", "order": "ASCENDING" }
      ]
    },
    {
      "collectionGroup": "hosts",
      "queryScope": "COLLECTION",
      "fields": [
        { "fieldPath": "role", "order": "ASCENDING" },
        { "fieldPath": "isActive", "order": "ASCENDING" }
      ]
    }
  ],
  "fieldOverrides": []
}
